ParserLexicalAnalyzer/__init__.py
ParserLexicalAnalyzer/dftParser.py
ParserLexicalAnalyzer/PropertyParser/LexicalAnalyzer.py
ParserLexicalAnalyzer/PropertyParser/Parser.py
ParserLexicalAnalyzer/PropertyParser/__init__.py
ParserLexicalAnalyzer/SimpleExpressionParser/LexicalAnalyzer.py
ParserLexicalAnalyzer/SimpleExpressionParser/Parser.py
ParserLexicalAnalyzer/SimpleExpressionParser/__init__.py
ParserLexicalAnalyzer/SystemModesParser/LexicalAnalyzer.py
ParserLexicalAnalyzer/SystemModesParser/Parser.py
ParserLexicalAnalyzer/SystemModesParser/__init__.py
ParserLexicalAnalyzer-1.1.1.dist-info/METADATA
ParserLexicalAnalyzer-1.1.1.dist-info/WHEEL
ParserLexicalAnalyzer-1.1.1.dist-info/top_level.txt
ParserLexicalAnalyzer-1.1.1.dist-info/RECORD
