Metadata-Version: 2.1
Name: ParserLexicalAnalyzer
Version: 1.1.1
Summary: Parser for simple arithmatic operation, boolean opreration and some advanced custom expressions for DFt's
Home-page: UNKNOWN
Author: Ahmad Waqas
Author-email: UNKNOWN
License: MIT
Platform: UNKNOWN
